nspd_package_p/__init__.py
nspd_package_p/nspd_p.py
nspd_parsels-0.1.9.dist-info/METADATA
nspd_parsels-0.1.9.dist-info/WHEEL
nspd_parsels-0.1.9.dist-info/entry_points.txt
nspd_parsels-0.1.9.dist-info/top_level.txt
nspd_parsels-0.1.9.dist-info/RECORD
